cloudselect/__init__.py
cloudselect/__main__.py
cloudselect/cloud.json.dist
cloudselect/cloudselect.py
cloudselect/instance.py
cloudselect/selector.py
cloudselect/discovery/__init__.py
cloudselect/discovery/aws.py
cloudselect/discovery/discovery.py
cloudselect/discovery/hetzner.py
cloudselect/discovery/kubernetes.py
cloudselect/discovery/local.py
cloudselect/discovery/stub.py
cloudselect/group/__init__.py
cloudselect/group/group.py
cloudselect/group/simple.py
cloudselect/group/stub.py
cloudselect/pathfinder/__init__.py
cloudselect/pathfinder/bastion.py
cloudselect/pathfinder/pathfinder.py
cloudselect/pathfinder/stub.py
cloudselect/report/__init__.py
cloudselect/report/json.py
cloudselect/report/json_pp.py
cloudselect/report/report.py
cloudselect/report/stub.py
cloudselect/report/yaml.py
test/__init__.py
test/conftest.py
test/test_cloudselect.py
test/test_options.py
test/test_selector.py
test/discovery/__init__.py
test/discovery/test_kubernetes.py
test/discovery/test_stub.py
test/group/__init__.py
test/group/test_simple.py
test/group/test_stub.py
test/pathfinder/__init__.py
test/pathfinder/test_bastion.py
test/pathfinder/test_stub.py
test/report/__init__.py
test/report/test_stub.py
cloudselect-20.1.14.dist-info/LICENSE
cloudselect-20.1.14.dist-info/METADATA
cloudselect-20.1.14.dist-info/WHEEL
cloudselect-20.1.14.dist-info/entry_points.txt
cloudselect-20.1.14.dist-info/top_level.txt
cloudselect-20.1.14.dist-info/RECORD
