Metadata-Version: 2.1
Name: cloudselect
Version: 20.1.14
Summary: FZF selector for cloud instances
Home-page: https://github.com/ezh/cloudselect
Author: Alexey Aksenov
Author-email: ezh@ezh.msk.ru
License: MIT
Download-URL: https://github.com/ezh/cloudselect/archive/v_01.tar.gz
Keywords: Cloud,CLI,FZF,SSH,SCP,AWS
Platform: UNKNOWN
Classifier: Development Status :: 4 - Beta
Classifier: Environment :: Console
Classifier: Intended Audience :: Information Technology
Classifier: Intended Audience :: System Administrators
Classifier: Topic :: System :: Distributed Computing
Classifier: Topic :: System :: Shells
Classifier: License :: OSI Approved :: MIT License
Classifier: Programming Language :: Python :: 3
Classifier: Programming Language :: Python :: 3.5
Classifier: Programming Language :: Python :: 3.6
Classifier: Programming Language :: Python :: 3.7
Classifier: Programming Language :: Python :: 3.8
Requires-Python: >=3
Requires-Dist: attrs (==19.3.0)
Requires-Dist: appdirs (==1.4.3)
Requires-Dist: boto3 (==1.12.5)
Requires-Dist: chardet (==3.0.4)
Requires-Dist: dependency-injector (==3.15.6)
Requires-Dist: hcloud (==1.6.3)
Requires-Dist: kubernetes (==10.0.1)
Requires-Dist: pyyaml (==5.3)
